LICENSE
MANIFEST.in
README.rst
setup.py
apps/mdjpp
mdjpp/__init__.py
mdjpp/options.py
mdjpp/parse.py
mdjpp/render.py
mdjpp/tags.py
mdjpp.egg-info/PKG-INFO
mdjpp.egg-info/SOURCES.txt
mdjpp.egg-info/dependency_links.txt
mdjpp.egg-info/not-zip-safe
mdjpp.egg-info/top_level.txt