Metadata-Version: 1.1
Name: mdjpp
Version: 0.1.2
Summary: Journal PreProcessor
Home-page: http://github.com/tljm/mdjpp
Author: Tomasz Magdziarz
Author-email: tljm@wp.pl
License: ISC
Platform: UNKNOWN
Classifier: Development Status :: 4 - Beta
Classifier: Environment :: Console
Classifier: License :: OSI Approved :: ISC License (ISCL)
Classifier: Programming Language :: Python :: 3 :: Only
Classifier: Topic :: Text Processing :: Markup
